{
  "project_info": {
    "project_number": "789203855732",
    "project_id": "skku-dm",
    "storage_bucket": "skku-dm.firebasestorage.app"
  },
  "client": [
    {
      "client_info": {
        "mobilesdk_app_id": "1:789203855732:android:d45fd5ddbfbd2aff2f6421",
        "android_client_info": {
          "package_name": "com.example.frontend"
        }
      },
      "oauth_client": [],
      "api_key": [
        {
          "current_key": "AIzaSyDJcOES-Dy7xVxvxtv0EaCRZ25FsBrWelg"
        }
      ],
      "services": {
        "appinvite_service": {
          "other_platform_oauth_client": []
        }
      }
    }
  ],
  "configuration_version": "1"
}